set_pdf_margins/__init__.py
set_pdf_margins/main.py
set_pdf_margins-0.1.1.dist-info/WHEEL
set_pdf_margins-0.1.1.dist-info/entry_points.txt
set_pdf_margins-0.1.1.dist-info/METADATA
set_pdf_margins-0.1.1.dist-info/RECORD
