Metadata-Version: 2.3
Name: set-pdf-margins
Version: 0.1.1
Summary: Place user-defined margins around PDF page content
Author: Niklas Kappel
Author-email: Niklas Kappel <niklas@kappel.com>
Classifier: Programming Language :: Python :: 3
Classifier: Operating System :: OS Independent
Requires-Dist: pypdf>=6.2.0
Requires-Dist: typer>=0.20.0
Requires-Python: >=3.10
Project-URL: Homepage, https://github.com/NiklasKappel/set-pdf-margins
Project-URL: Issues, https://github.com/NiklasKappel/set-pdf-margins/issues
